manisble/__init__.py
manisble/airflow/__init__.py
manisble/airflow/airflow.py
manisble/awx/awx_common.py
manisble/awx/awx_credential.py
manisble/awx/awx_executionenvironments.py
manisble/awx/awx_hosts.py
manisble/awx/awx_organisation.py
manisble/awx/awx_project.py
manisble/awx_common.py
manisble/bump/__init__.py
manisble/bump/bump.py
manisble/common.py
manisble/dns/__init__.py
manisble/dns/cloudflare.py
manisble/dns/dns.py
manisble/gitea/__init__.py
manisble/gitea/git.py
manisble/inabox/__init__.py
manisble/inabox/inabox.py
manisble/inabox/virtlib.py
manisble/inthevault/__init__.py
manisble/inthevault/inthevault.py
manisble/jenkins/__init__.py
manisble/jenkins/jenkins.py
manisble/manisble.py
manisble/netbox/__init__.py
manisble/netbox/clusters.py
manisble/netbox/common.py
manisble/netbox/netbox.py
manisble/netbox/netbox_ipaddress.py
manisble/netbox/netbox_server.py
manisble/netbox/organization.py
manisble/netbox/redis.py
manisble/netbox/serve.py
manisble/netbox/subprojects.py
manisble/package_data.dat
manisble/pitv/__init__.py
manisble/pitv/pitv.py
manisble/pypi/__init__.py
manisble/pypi/pypi.py
manisble/semaphore/__init__.py
manisble/semaphore/git.py
manisble/semaphore/semaphore.py
manisble/semaphore/serve.py
manisble/semapore.sh
manisble/ssh/__init__.py
manisble/ssh/ssh.py
manisble/toolbox.py
manisble/traefik/__init__.py
manisble/traefik/traefik.py
manisble/ui/__init__.py
manisble/ui/serve.py
manisble/ui/ui.py
manisble/vmware/__init__.py
manisble/vmware/getvmsbycluster.py
manisble/vmware/helloworld.py
manisble/vmware/requirements.txt
manisble/vmware/serve.py
manisble/vmware/tools/README.md
manisble/vmware/tools/__init__.py
manisble/vmware/tools/alarm.py
manisble/vmware/tools/cli.py
manisble/vmware/tools/cluster.py
manisble/vmware/tools/datacenter.py
manisble/vmware/tools/disk.py
manisble/vmware/tools/interactive_wrapper.py
manisble/vmware/tools/pbmhelper.py
manisble/vmware/tools/pchelper.py
manisble/vmware/tools/service_instance.py
manisble-0.1.12.dist-info/LICENSE.txt
manisble-0.1.12.dist-info/METADATA
manisble-0.1.12.dist-info/WHEEL
manisble-0.1.12.dist-info/entry_points.txt
manisble-0.1.12.dist-info/RECORD
