Metadata-Version: 2.1
Name: manisble
Version: 0.1.12
Summary: Manageable Ansible
Home-page: https://manisble.awx.wiki
License: MIT
Author: Martin Juhl Prendergast
Author-email: m@rtinjuhl.dk
Requires-Python: >=3.8,<4.0
Classifier: License :: OSI Approved :: MIT License
Classifier: Programming Language :: Python :: 3
Classifier: Programming Language :: Python :: 3.8
Classifier: Programming Language :: Python :: 3.9
Classifier: Programming Language :: Python :: 3.10
Classifier: Programming Language :: Python :: 3.11
Classifier: Programming Language :: Python :: 3.12
Requires-Dist: PyYAML (>=6.0.1,<7.0.0)
Requires-Dist: cryptography (>=41.0.2,<42.0.0)
Requires-Dist: hvac (>=1.1.0,<2.0.0)
Requires-Dist: mypy (>=0.910,<0.911)
Requires-Dist: netbox (>=0.0.2,<0.0.3)
Requires-Dist: paramiko (>=3.3.1,<4.0.0)
Requires-Dist: pynetbox (>=6.6.2,<7.0.0)
Requires-Dist: pytest (>=6.2,<7.0)
Requires-Dist: python-jenkins (>=1.7.0,<2.0.0)
Requires-Dist: pyvmomi (>=8.0.2.0.1,<9.0.0.0.0)
Requires-Dist: redis (>=4.5.3,<5.0.0)
Requires-Dist: requests (>=2.25,<3.0)
Requires-Dist: toml (>=0.10.2,<0.11.0)
Requires-Dist: xmltodict (>=0.13.0,<0.14.0)
Project-URL: Repository, https://github.com/MrMEEE/manisble.git
